blockchain/__init__.py
blockchain/neo/__init__.py
blockchain/neo/ingest.py
blockchain/neo/switcheo.py
blockchain_etl-0.1.31.dist-info/METADATA
blockchain_etl-0.1.31.dist-info/RECORD
blockchain_etl-0.1.31.dist-info/WHEEL
blockchain_etl-0.1.31.dist-info/top_level.txt
